{
  "model_info": {
    "model_name": "ViT-B/32",
    "confidence_threshold": 0.3,
    "num_photos": 5,
    "device": "cpu"
  },
  "photos": [
    {
      "filename": "Figure 59.jpg",
      "total_detections": 1,
      "category_counts": {
        "church or cathedral": 1
      },
      "priority_score": 0.0,
      "detections": [
        {
          "category": "church or cathedral",
          "confidence": 0.3616485893726349,
          "category_id": 17,
          "historical_context": "Historical relevance"
        }
      ],
      "top_categories": [
        "church or cathedral"
      ]
    },
    {
      "filename": "Figure 26a.jpg",
      "total_detections": 1,
      "category_counts": {
        "group of people": 1
      },
      "priority_score": 0.0,
      "detections": [
        {
          "category": "group of people",
          "confidence": 0.6682491898536682,
          "category_id": 7,
          "historical_context": "Historical relevance"
        }
      ],
      "top_categories": [
        "group of people"
      ]
    },
    {
      "filename": "\u05d2\u05e8\u05d8\u05e8\u05d5\u05d3+ \u05d0\u05d5\u05d8\u05d5 \u05e8\u05d3\u05d4 1935-6 001.jpg",
      "total_detections": 1,
      "category_counts": {
        "wedding photograph": 1
      },
      "priority_score": 0.0,
      "detections": [
        {
          "category": "wedding photograph",
          "confidence": 0.6917311549186707,
          "category_id": 6,
          "historical_context": "Historical relevance"
        }
      ],
      "top_categories": [
        "wedding photograph"
      ]
    },
    {
      "filename": "Figure 67.jpg",
      "total_detections": 1,
      "category_counts": {
        "farming equipment": 1
      },
      "priority_score": 0.0,
      "detections": [
        {
          "category": "farming equipment",
          "confidence": 0.5673567652702332,
          "category_id": 38,
          "historical_context": "Historical relevance"
        }
      ],
      "top_categories": [
        "farming equipment"
      ]
    },
    {
      "filename": "Figure 66.jpg",
      "total_detections": 1,
      "category_counts": {
        "children playing": 1
      },
      "priority_score": 0.0,
      "detections": [
        {
          "category": "children playing",
          "confidence": 0.3168483078479767,
          "category_id": 4,
          "historical_context": "Historical relevance"
        }
      ],
      "top_categories": [
        "children playing"
      ]
    }
  ]
}